paubox/__init__.py
paubox/paubox.py
paubox/helpers/__init__.py
paubox/helpers/errors.py
paubox/helpers/mail.py
test/__init__.py
test/test_paubox.py
paubox_python-0.0.3.dist-info/LICENSE
paubox_python-0.0.3.dist-info/METADATA
paubox_python-0.0.3.dist-info/WHEEL
paubox_python-0.0.3.dist-info/top_level.txt
paubox_python-0.0.3.dist-info/RECORD
