Metadata-Version: 2.1
Name: paubox-python
Version: 0.0.3
Summary: Python SDK for Paubox Email REST API
Home-page: https://github.com/Paubox/paubox-python
Author: Paubox
Author-email: info@paubox.com
License: UNKNOWN
Platform: UNKNOWN
Classifier: Programming Language :: Python :: 2.7
Classifier: License :: OSI Approved :: Apache Software License
